yggdrasilpylint/__init__.py
yggdrasilpylint/__main__.py
yggdrasilpylint/analyzers/basic.py
yggdrasilpylint/linter/basic.py
yggdrasilpylint/linter/violations.py
yggdrasilpylint-0.1.0.dist-info/LICENSE
yggdrasilpylint-0.1.0.dist-info/METADATA
yggdrasilpylint-0.1.0.dist-info/WHEEL
yggdrasilpylint-0.1.0.dist-info/RECORD
