Metadata-Version: 2.1
Name: yggdrasilpylint
Version: 0.1.0
Summary: Simple, high-quality, beautiful linter and analyzer for Python
License: GNU LGPL 2.1
Author: alexeev-prog
Author-email: alexeev.dev@mail.ru
Requires-Python: >=3.9,<4.0
Classifier: License :: Other/Proprietary License
Classifier: Programming Language :: Python :: 3
Classifier: Programming Language :: Python :: 3.9
Classifier: Programming Language :: Python :: 3.10
Classifier: Programming Language :: Python :: 3.11
Classifier: Programming Language :: Python :: 3.12
Requires-Dist: click (>=8.1.7,<9.0.0)
Requires-Dist: rich (>=13.9.4,<14.0.0)
